odoo9_addon_account_due_list_aging_comments-9.0.0.1.0-py2.7-nspkg.pth
odoo9_addon_account_due_list_aging_comments-9.0.0.1.0.dist-info/DESCRIPTION.rst
odoo9_addon_account_due_list_aging_comments-9.0.0.1.0.dist-info/METADATA
odoo9_addon_account_due_list_aging_comments-9.0.0.1.0.dist-info/RECORD
odoo9_addon_account_due_list_aging_comments-9.0.0.1.0.dist-info/WHEEL
odoo9_addon_account_due_list_aging_comments-9.0.0.1.0.dist-info/metadata.json
odoo9_addon_account_due_list_aging_comments-9.0.0.1.0.dist-info/namespace_packages.txt
odoo9_addon_account_due_list_aging_comments-9.0.0.1.0.dist-info/top_level.txt
odoo_addons/account_due_list_aging_comments/README.rst
odoo_addons/account_due_list_aging_comments/__init__.py
odoo_addons/account_due_list_aging_comments/__openerp__.py
odoo_addons/account_due_list_aging_comments/i18n/de.po
odoo_addons/account_due_list_aging_comments/i18n/es.po
odoo_addons/account_due_list_aging_comments/i18n/it.po
odoo_addons/account_due_list_aging_comments/i18n/pt_BR.po
odoo_addons/account_due_list_aging_comments/i18n/sl.po
odoo_addons/account_due_list_aging_comments/models/__init__.py
odoo_addons/account_due_list_aging_comments/models/account_move_line.py
odoo_addons/account_due_list_aging_comments/static/description/icon.png
odoo_addons/account_due_list_aging_comments/views/payment_view.xml
